mwcp/__init__.py
mwcp/cli.py
mwcp/core.py
mwcp/dispatcher.py
mwcp/exceptions.py
mwcp/file_object.py
mwcp/metadata.py
mwcp/parser.py
mwcp/parser_config.yml
mwcp/registry.py
mwcp/report.py
mwcp/report_writers.py
mwcp/runner.py
mwcp/tester.py
mwcp/testing.py
mwcp/config/__init__.py
mwcp/config/config.yml
mwcp/config/fields.json
mwcp/config/fields.txt
mwcp/config/log_config.yml
mwcp/config/schema.json
mwcp/parsers/Archive.py
mwcp/parsers/Decoy.py
mwcp/parsers/GenericDropper.py
mwcp/parsers/ISO.py
mwcp/parsers/PDF.py
mwcp/parsers/PowerShell.py
mwcp/parsers/Python.py
mwcp/parsers/Quarantined.py
mwcp/parsers/RSA.py
mwcp/parsers/TA.py
mwcp/parsers/VisualBasic.py
mwcp/parsers/__init__.py
mwcp/parsers/foo.py
mwcp/parsers/tests/foo/f144899b86766688991c5d0d10902f4a.json
mwcp/resources/__init__.py
mwcp/resources/techanarchy_bridge.py
mwcp/resources/RATDecoders/PLACE_PARSERS_HERE
mwcp/resources/RATDecoders/__init__.py
mwcp/stix/__init__.py
mwcp/stix/extensions.py
mwcp/stix/objects.py
mwcp/stix/report_writer.py
mwcp/tests/__init__.py
mwcp/tests/conftest.py
mwcp/tests/construct_html.html
mwcp/tests/test_cli.py
mwcp/tests/test_construct.py
mwcp/tests/test_custombase64.py
mwcp/tests/test_disassembly.py
mwcp/tests/test_dispatcher.py
mwcp/tests/test_issues.py
mwcp/tests/test_legacy_reporter.py
mwcp/tests/test_metadata.py
mwcp/tests/test_parsers.py
mwcp/tests/test_pecon.py
mwcp/tests/test_poshdeob.py
mwcp/tests/test_registry.py
mwcp/tests/test_report.py
mwcp/tests/test_report_writer.py
mwcp/tests/test_runner.py
mwcp/tests/test_server.py
mwcp/tests/test_stix.py
mwcp/tests/test_string_report.py
mwcp/tests/test_testing.py
mwcp/tests/test_cli/csv_cli.csv
mwcp/tests/test_cli/csv_legacy.csv
mwcp/tests/test_cli/fb843efb2ffec987db12e72ca75c9ea2.json
mwcp/tests/test_cli/parse.json
mwcp/tests/test_cli/parse.txt
mwcp/tests/test_disassembly/Sample.py
mwcp/tests/test_disassembly/strings.c
mwcp/tests/test_disassembly/strings.exe
mwcp/tests/test_disassembly/strings.json
mwcp-3.14.0.dist-info/LICENSE.txt
mwcp-3.14.0.dist-info/METADATA
mwcp-3.14.0.dist-info/WHEEL
mwcp-3.14.0.dist-info/entry_points.txt
mwcp-3.14.0.dist-info/top_level.txt
mwcp-3.14.0.dist-info/RECORD
