Metadata-Version: 2.1
Name: mwcp
Version: 3.14.0
Summary: A framework for malware configuration parsers.
Home-page: https://github.com/dod-cyber-crime-center/DC3-MWCP/
Author: DC3
Author-email: dc3.tsd@us.af.mil
License: MIT
Keywords: malware
Classifier: Development Status :: 5 - Production/Stable
Classifier: Intended Audience :: Developers
Classifier: License :: OSI Approved :: MIT License
Classifier: Programming Language :: Python :: 3
Classifier: Programming Language :: Python :: 3.9
Classifier: Programming Language :: Python :: 3.10
Classifier: Programming Language :: Python :: 3.11
Classifier: Programming Language :: Python :: 3.12
Requires-Python: >=3.9
License-File: LICENSE.txt
Requires-Dist: anytree
Requires-Dist: appdirs
Requires-Dist: attrs >=20.3.0
Requires-Dist: bitarray
Requires-Dist: cattrs
Requires-Dist: click >=8.0.1
Requires-Dist: construct <2.11,>=2.9.45
Requires-Dist: defusedxml
Requires-Dist: future
Requires-Dist: isodate
Requires-Dist: jinja2
Requires-Dist: jsonschema-extractor >=1.0
Requires-Dist: packaging
Requires-Dist: pandas
Requires-Dist: pefile >=2019.4.18
Requires-Dist: pyasn1
Requires-Dist: pyasn1-modules
Requires-Dist: pyelftools
Requires-Dist: pyparsing
Requires-Dist: pytest >=6.0.0
Requires-Dist: pytest-datadir
Requires-Dist: pytest-xdist
Requires-Dist: pytest-mock
Requires-Dist: pytest-cov
Requires-Dist: pyyaml
Requires-Dist: requests
Requires-Dist: ruamel.yaml
Requires-Dist: six
Requires-Dist: tabulate[widechars] <1.0.0
Requires-Dist: stix2
Requires-Dist: yara-python
Requires-Dist: flask
Requires-Dist: pygments
Requires-Dist: pycdlib
Requires-Dist: pycryptodome
Requires-Dist: olefile
Provides-Extra: dragodis
Requires-Dist: dragodis >=0.2.0 ; extra == 'dragodis'
Provides-Extra: kordesii
Requires-Dist: kordesii >=2.0.0 ; extra == 'kordesii'
Provides-Extra: testing
Requires-Dist: jsonschema ; extra == 'testing'
Requires-Dist: dragodis ; extra == 'testing'
Requires-Dist: rugosa ; extra == 'testing'
